covariance_selection_algorithm/__init__.py
covariance_selection_algorithm/algorithm.py
tests/__init__.py
tests/unit/__init__.py
tests/unit/test_calculate.py
dempsters_algorithm-0.0.1.dist-info/METADATA
dempsters_algorithm-0.0.1.dist-info/WHEEL
dempsters_algorithm-0.0.1.dist-info/top_level.txt
dempsters_algorithm-0.0.1.dist-info/RECORD
